<DOMSymbolItem xmlns:xsi="http://www.w3.org/2001/XMLSchema-instance" xmlns="http://ns.adobe.com/xfl/2008/" name="Star" itemID="518e6a57-000001d4" linkageExportForAS="true" linkageClassName="starart" lastModified="1368301830">
  <timeline>
    <DOMTimeline name="Star">
      <layers>
        <DOMLayer name="Layer 1" color="#4FFF4F" current="true" isSelected="true">
          <frames>
            <DOMFrame index="0" keyMode="9728">
              <elements>
                <DOMShape>
                  <fills>
                    <FillStyle index="1">
                      <RadialGradient>
                        <matrix>
                          <Matrix a="0.0098876953125" d="0.002471923828125"/>
                        </matrix>
                        <GradientEntry color="#D4FFFF" ratio="0.172549019607843"/>
                        <GradientEntry ratio="1"/>
                      </RadialGradient>
                    </FillStyle>
                  </fills>
                  <strokes>
                    <StrokeStyle index="1">
                      <SolidStroke scaleMode="normal" weight="0.1">
                        <fill>
                          <SolidColor/>
                        </fill>
                      </SolidStroke>
                    </StrokeStyle>
                  </strokes>
                  <edges>
                    <Edge fillStyle1="1" edges="!-48 -38[#FFFFE6.5D -40 0 -40!0 -40[68 -40 112 -28!112 -28[160 -16 160 0!160 0[160 17 112 28!112 28[68 40 0 40!0 40[#FFFFE6.5E 40 -48 38"/>
                    <Edge strokeStyle="1" edges="!-48 38[#FFFFCA.82 40 -60 40!-60 40[#FFFFB8.AB 40 -80 34.5"/>
                    <Edge fillStyle1="1" edges="!-80 34.5[#FFFF9E.AB 32 -112 28!-112 28[-160 17 -160 0!-160 0[-160 -16 -112 -28!-112 -28[-97.328125 -32 -80 -34.5"/>
                    <Edge strokeStyle="1" edges="!-80 -34.5[#FFFFB8.AD -40 -60 -40!-60 -40[#FFFFCA.81 -40 -48 -38"/>
                    <Edge fillStyle1="1" edges="!-80 -34.5[-64.9375 -36.890625 -48 -38!-48 38[-64.9375 #24.E4 -80 34.5"/>
                  </edges>
                </DOMShape>
              </elements>
            </DOMFrame>
          </frames>
        </DOMLayer>
      </layers>
    </DOMTimeline>
  </timeline>
</DOMSymbolItem>